{
  "name": "Kaneohe Sandbar (Ahu o Laka)",
  "tier": "A",
  "lat": 21.4622,
  "lng": -157.8060,
  "category": "kids",
  "subcategory": "nature",
  "tagline": "A sandbar in the middle of Kaneohe Bay where you stand in knee-deep turquoise water with the Koolaus as backdrop.",
  "area": "Kaneohe",
  "price": "$$",
  "parking": "Park at Heeia Kea Boat Harbor; various tour operators depart from here",
  "hours": "Tour operators run morning and afternoon trips; sandbar accessible during low tide",
  "bestTime": "Low tide for maximum sandbar exposure; morning trips for calmer water and better light",
  "kidFriendly": true,
  "kamaaina": "Some tour operators offer kamaaina rates — ask when booking",
  "talkStory": "Good for ages 2 and up. At low tide, the water is shin-deep on the sandbar — perfect for toddlers to splash around safely. Bring your own kayak or SUP to save money, or book a boat tour that includes gear. The views of Chinaman's Hat and the Koolau Mountains from the sandbar are unreal. Bring reef-safe sunscreen, snacks, and a pop-up shade if you have one. Check tide charts before you go — at high tide the sandbar disappears."
}
